LICENSE
MANIFEST.in
README.md
setup.py
extern/HepMC3/include/HepMC3/AssociatedParticle.h
extern/HepMC3/include/HepMC3/Attribute.h
extern/HepMC3/include/HepMC3/Errors.h
extern/HepMC3/include/HepMC3/FourVector.h
extern/HepMC3/include/HepMC3/GenCrossSection.h
extern/HepMC3/include/HepMC3/GenCrossSection_fwd.h
extern/HepMC3/include/HepMC3/GenEvent.h
extern/HepMC3/include/HepMC3/GenHeavyIon.h
extern/HepMC3/include/HepMC3/GenHeavyIon_fwd.h
extern/HepMC3/include/HepMC3/GenParticle.h
extern/HepMC3/include/HepMC3/GenParticle_fwd.h
extern/HepMC3/include/HepMC3/GenPdfInfo.h
extern/HepMC3/include/HepMC3/GenPdfInfo_fwd.h
extern/HepMC3/include/HepMC3/GenRunInfo.h
extern/HepMC3/include/HepMC3/GenVertex.h
extern/HepMC3/include/HepMC3/GenVertex_fwd.h
extern/HepMC3/include/HepMC3/HEPEVT_Wrapper.h
extern/HepMC3/include/HepMC3/HepMC3.h
extern/HepMC3/include/HepMC3/LHEF.h
extern/HepMC3/include/HepMC3/LHEFAttributes.h
extern/HepMC3/include/HepMC3/Print.h
extern/HepMC3/include/HepMC3/PrintStreams.h
extern/HepMC3/include/HepMC3/Reader.h
extern/HepMC3/include/HepMC3/ReaderAscii.h
extern/HepMC3/include/HepMC3/ReaderAsciiHepMC2.h
extern/HepMC3/include/HepMC3/ReaderFactory.h
extern/HepMC3/include/HepMC3/ReaderHEPEVT.h
extern/HepMC3/include/HepMC3/ReaderLHEF.h
extern/HepMC3/include/HepMC3/ReaderPlugin.h
extern/HepMC3/include/HepMC3/Setup.h
extern/HepMC3/include/HepMC3/Units.h
extern/HepMC3/include/HepMC3/Version.h
extern/HepMC3/include/HepMC3/Writer.h
extern/HepMC3/include/HepMC3/WriterAscii.h
extern/HepMC3/include/HepMC3/WriterAsciiHepMC2.h
extern/HepMC3/include/HepMC3/WriterHEPEVT.h
extern/HepMC3/include/HepMC3/WriterPlugin.h
extern/HepMC3/include/HepMC3/Data/GenEventData.h
extern/HepMC3/include/HepMC3/Data/GenParticleData.h
extern/HepMC3/include/HepMC3/Data/GenRunInfoData.h
extern/HepMC3/include/HepMC3/Data/GenVertexData.h
extern/HepMC3/src/GenCrossSection.cc
extern/HepMC3/src/GenEvent.cc
extern/HepMC3/src/GenHeavyIon.cc
extern/HepMC3/src/GenParticle.cc
extern/HepMC3/src/GenPdfInfo.cc
src/pyhepmc_ng.egg-info/PKG-INFO
src/pyhepmc_ng.egg-info/SOURCES.txt
src/pyhepmc_ng.egg-info/dependency_links.txt
src/pyhepmc_ng.egg-info/not-zip-safe
src/pyhepmc_ng.egg-info/requires.txt
src/pyhepmc_ng.egg-info/top_level.txt